{
  "id": "Secciones/Arquitectura",
  "title": "Arquitectura del sistema",
  "description": "Descripción General",
  "source": "@site/versioned_docs/version-1.0/Secciones/Arquitectura.md",
  "sourceDirName": "Secciones",
  "slug": "/Secciones/Arquitectura",
  "permalink": "/en/docs/1.0/Secciones/Arquitectura",
  "draft": false,
  "unlisted": false,
  "editUrl": "https://github.com/JuanToSeidor/DocuDaiana/tree/master/versioned_docs/version-1.0/Secciones/Arquitectura.md",
  "tags": [],
  "version": "1.0",
  "sidebarPosition": 1,
  "frontMatter": {
    "title": "Arquitectura del sistema",
    "sidebar_position": 1
  },
  "sidebar": "tutorialSidebar",
  "previous": {
    "title": "Empezamos con DAIANA",
    "permalink": "/en/docs/1.0/intro"
  },
  "next": {
    "title": "Operación del Sistema",
    "permalink": "/en/docs/1.0/Secciones/operaciones"
  }
}